manimpro/__init__.py
manimpro/__main__.py
manimpro/constants.py
manimpro/data_structures.py
manimpro/typing.py
manimpro/web_viewer.py
manimpro/_config/__init__.py
manimpro/_config/cli_colors.py
manimpro/_config/default.cfg
manimpro/_config/logger_utils.py
manimpro/_config/utils.py
manimpro/animation/__init__.py
manimpro/animation/animation.py
manimpro/animation/changing.py
manimpro/animation/composition.py
manimpro/animation/creation.py
manimpro/animation/fading.py
manimpro/animation/growing.py
manimpro/animation/indication.py
manimpro/animation/movement.py
manimpro/animation/numbers.py
manimpro/animation/rotation.py
manimpro/animation/specialized.py
manimpro/animation/speedmodifier.py
manimpro/animation/transform.py
manimpro/animation/transform_matching_parts.py
manimpro/animation/updaters/__init__.py
manimpro/animation/updaters/mobject_update_utils.py
manimpro/animation/updaters/update.py
manimpro/camera/__init__.py
manimpro/camera/camera.py
manimpro/camera/mapping_camera.py
manimpro/camera/moving_camera.py
manimpro/camera/multi_camera.py
manimpro/camera/three_d_camera.py
manimpro/cli/__init__.py
manimpro/cli/default_group.py
manimpro/cli/cfg/__init__.py
manimpro/cli/cfg/group.py
manimpro/cli/checkhealth/__init__.py
manimpro/cli/checkhealth/checks.py
manimpro/cli/checkhealth/commands.py
manimpro/cli/init/__init__.py
manimpro/cli/init/commands.py
manimpro/cli/plugins/__init__.py
manimpro/cli/plugins/commands.py
manimpro/cli/preview/__init__.py
manimpro/cli/preview/commands.py
manimpro/cli/render/__init__.py
manimpro/cli/render/commands.py
manimpro/cli/render/ease_of_access_options.py
manimpro/cli/render/global_options.py
manimpro/cli/render/output_options.py
manimpro/cli/render/render_options.py
manimpro/cli/wizard/__init__.py
manimpro/cli/wizard/commands.py
manimpro/easy/__init__.py
manimpro/easy/achievements.py
manimpro/easy/challenges.py
manimpro/easy/examples.py
manimpro/easy/inspiration.py
manimpro/easy/presets.py
manimpro/easy/progress.py
manimpro-0.7.2.dist-info/METADATA
manimpro-0.7.2.dist-info/WHEEL
manimpro-0.7.2.dist-info/entry_points.txt
manimpro-0.7.2.dist-info/licenses/LICENSE
manimpro-0.7.2.dist-info/licenses/LICENSE.community
manimpro-0.7.2.dist-info/RECORD
