Metadata-Version: 2.4
Name: manimpro
Version: 0.7.2
Summary: ManimPro: High-quality, portable, and user-friendly mathematical animation engine. Forked from Manim Community.
Project-URL: repository, https://github.com/manimpro/manimpro
Project-URL: documentation, https://docs.manimpro.org/
Project-URL: homepage, https://www.manimpro.org/
Project-URL: Bug Tracker, https://github.com/manimpro/manimpro/issues
Project-URL: Changelog, https://docs.manimpro.org/en/stable/changelog.html
Project-URL: Discord, https://www.manimpro.org/discord/
Author-email: The ManimPro Developers <contact@manimpro.org>
License-Expression: MIT
License-File: LICENSE
License-File: LICENSE.community
Classifier: Development Status :: 4 - Beta
Classifier: License :: OSI Approved :: MIT License
Classifier: Natural Language :: English
Classifier: Programming Language :: Python :: 3.9
Classifier: Programming Language :: Python :: 3.10
Classifier: Programming Language :: Python :: 3.11
Classifier: Programming Language :: Python :: 3.12
Classifier: Topic :: Multimedia :: Graphics
Classifier: Topic :: Multimedia :: Video
Classifier: Topic :: Scientific/Engineering
Requires-Python: >=3.9
Requires-Dist: audioop-lts>=0.2.1; python_full_version >= '3.13'
Requires-Dist: av<16.0.0,>=10.0.0
Requires-Dist: beautifulsoup4>=4.12
Requires-Dist: click>=8.0
Requires-Dist: cloup>=2.0.0
Requires-Dist: decorator>=4.3.2
Requires-Dist: importlib-metadata>=8.6.1; python_full_version < '3.10'
Requires-Dist: isosurfaces>=0.1.0
Requires-Dist: manimpango<1.0.0,>=0.5.0
Requires-Dist: mapbox-earcut>=1.0.0
Requires-Dist: moderngl-window>=2.0.0
Requires-Dist: moderngl<6.0.0,>=5.0.0
Requires-Dist: networkx>=2.6
Requires-Dist: numpy>=2.1; python_full_version >= '3.10'
Requires-Dist: numpy>=2.3.3
Requires-Dist: pillow>=9.1
Requires-Dist: pycairo<2.0.0,>=1.13
Requires-Dist: pydub>=0.20.0
Requires-Dist: pygments>=2.0.0
Requires-Dist: rich>=12.0.0
Requires-Dist: scipy>=1.13.0
Requires-Dist: scipy>=1.14.0; python_full_version >= '3.13'
Requires-Dist: screeninfo>=0.7
Requires-Dist: skia-pathops>=0.7.0
Requires-Dist: srt>=3.0.0
Requires-Dist: svgelements>=1.8.0
Requires-Dist: tqdm>=4.0.0
Requires-Dist: typing-extensions>=4.12.0
Requires-Dist: watchdog>=2.0.0
Provides-Extra: gui
Requires-Dist: dearpygui>=1.0.0; extra == 'gui'
Provides-Extra: jupyterlab
Requires-Dist: jupyterlab>=4.3.4; extra == 'jupyterlab'
Requires-Dist: notebook>=7.3.2; extra == 'jupyterlab'
Provides-Extra: webviewer
Requires-Dist: fastapi>=0.104.0; extra == 'webviewer'
Requires-Dist: uvicorn>=0.24.0; extra == 'webviewer'
